markers/__init__.py
markers/_version.py
markers/api.py
markers/cycle.py
markers/document.py
markers/label.py
markers/label_batch.py
markers/labeler.py
markers/markers.py
markers/project.py
markers/queries.py
markers/task.py
markers/uploader.py
markers/utils.py
markers/static/extension.js
markers/static/index.js
markers/static/index.js.map
markers-0.3.0.data/data/etc/jupyter/nbconfig/notebook.d/markers.json
markers-0.3.0.data/data/share/jupyter/nbextensions/markers/extension.js
markers-0.3.0.data/data/share/jupyter/nbextensions/markers/index.js
markers-0.3.0.data/data/share/jupyter/nbextensions/markers/index.js.map
markers-0.3.0.dist-info/LICENSE
markers-0.3.0.dist-info/METADATA
markers-0.3.0.dist-info/WHEEL
markers-0.3.0.dist-info/top_level.txt
markers-0.3.0.dist-info/RECORD
