Metadata-Version: 2.1
Name: markers
Version: 0.3.0
Summary: A data labeling widget for use with Markers.ai
Home-page: https://markers.ai
Author: Andrew Sullivan
Author-email: andrew@markers.ai
License: Apache 2.0
Keywords: markers,machine learning,data science,annotation,labeling
Platform: UNKNOWN
Classifier: Development Status :: 4 - Beta
Classifier: Framework :: IPython
Classifier: Intended Audience :: Developers
Classifier: Intended Audience :: Science/Research
Classifier: Topic :: Multimedia :: Graphics
Classifier: Programming Language :: Python :: 3
Classifier: Programming Language :: Python :: 3.6
Classifier: Programming Language :: Python :: 3.7
Requires-Dist: ipywidgets (>=7.0.0)
Requires-Dist: pandas (>=0.20.0)
Requires-Dist: requests (>=2.0.0)
Requires-Dist: tqdm (>=4.0.0)
